{
  "version": "rp-v4-trade-improve",
  "updated_at": "2026-03-09T21:55:00+09:00",
  "min_scale": 0.28,
  "block_rate_soft_limit": 0.78,
  "activity_rate_floor": 0.55,
  "block_to_reduce_scale": 0.52,
  "reduce_to_allow_scale": 0.8,
  "guard_window_decisions": 180,
  "min_guard_samples": 40,
  "max_block_streak": 10,
  "outcome_min_trades": 12,
  "outcome_positive_pf_floor": 1.02,
  "outcome_positive_win_rate_floor": 0.47,
  "notes": [
    "Prefer throughput with controlled scaling instead of hard blocking.",
    "Relax shallow reductions back to ALLOW only when setup quality is strong and execution quality is still normal."
  ]
}
